[
  {
    "comments": [],
    "compensationAndBenefitsRating": {
      "rating": 4,
      "type": "Compensation/Benefits"
    },
    "country": "RU",
    "cultureAndValuesRating": {
      "rating": 5,
      "type": "Job Culture"
    },
    "currentEmployee": true,
    "encryptedReviewId": "f7cbf15c484bd01e",
    "headerTitle": "ОАО \"РЖД\" Оператор при ДСП Review - Сложно, но весело",
    "helpful": 0,
    "indexable": true,
    "isDeletable": false,
    "jobSecurityAndAdvancementRating": {
      "rating": 4,
      "type": "Job Security/Advancement"
    },
    "jobTitle": "Оператор при ДСП",
    "jobTitleFilterLink": "/cmp/%D0%9E%D0%B0%D0%BE-%22%D1%80%D0%B6%D0%B4%22/reviews?fjobtitle=%D0%9E%D0%BF%D0%B5%D1%80%D0%B0%D1%82%D0%BE%D1%80",
    "location": "Нижний Новгород-Московский ",
    "locationFilterLink": "/cmp/%D0%9E%D0%B0%D0%BE-%22%D1%80%D0%B6%D0%B4%22/reviews?fcountry=RU&floc=%D0%9D%D0%B8%D0%B6%D0%BD%D0%B8%D0%B9+%D0%9D%D0%BE%D0%B2%D0%B3%D0%BE%D1%80%D0%BE%D0%B4",
    "managementRating": {
      "rating": 3,
      "type": "Management"
    },
    "normJobTitle": "Оператор",
    "overallRating": 5,
    "redacted": false,
    "reviewUid": "1ft26v2on3nm5000",
    "reviewUrl": "/cmp/%D0%9E%D0%B0%D0%BE-%22%D1%80%D0%B6%D0%B4%22/reviews/%D1%81%D0%BB%D0%BE%D0%B6%D0%BD%D0%BE-%D0%BD%D0%BE-%D0%B2%D0%B5%D1%81%D0%B5%D0%BB%D0%BE?id=f7cbf15c484bd01e",
    "sharingLink": "https://www.indeed.com/cmp/%D0%9E%D0%B0%D0%BE-%22%D1%80%D0%B6%D0%B4%22/reviews/%D1%81%D0%BB%D0%BE%D0%B6%D0%BD%D0%BE-%D0%BD%D0%BE-%D0%B2%D0%B5%D1%81%D0%B5%D0%BB%D0%BE?id=f7cbf15c484bd01e",
    "submissionDate": "March 1, 2022",
    "text": {
      "languageTag": "ru-RU",
      "text": "Потрясающий коллектив, работа в основном однообразная, но, тем не менее, сложных задач даже через год работы хватает. Зарплата, по моему мнению, не соответствует кругу обязанностей и ответственности, но ее хватает. Льготы в виде бесплатного проезда до работы, бесплатного поезда раз в год до любой станции и всяких плюшек от профсоюза-тоже приятная особенность "
    },
    "title": {
      "languageTag": "ru-RU",
      "text": "Сложно, но весело"
    },
    "tweetAutoFillText": "ОАО \"РЖД\" review on #indeedjobs: \"Сложно, но весело\"",
    "type": "LIST",
    "unhelpful": 0,
    "workAndLifeBalanceRating": {
      "rating": 2,
      "type": "Job Work/Life Balance"
    }
  },
  {
    "comments": [],
    "compensationAndBenefitsRating": {
      "rating": 5,
      "type": "Compensation/Benefits"
    },
    "country": "RU",
    "cultureAndValuesRating": {
      "rating": 5,
      "type": "Job Culture"
    },
    "currentEmployee": false,
    "encryptedReviewId": "75ec9a09e9202e57",
    "headerTitle": "ОАО \"РЖД\" 30 лет Review - Ответственная интересная работа ",
    "helpful": 0,
    "indexable": false,
    "isDeletable": false,
    "jobSecurityAndAdvancementRating": {
      "rating": 5,
      "type": "Job Security/Advancement"
    },
    "jobTitle": "30 лет",
    "jobTitleFilterLink": "/cmp/%D0%9E%D0%B0%D0%BE-%22%D1%80%D0%B6%D0%B4%22/reviews?fjobtitle=30+%D0%BB%D0%B5%D1%82",
    "location": "Ст Плесецкая ",
    "managementRating": {
      "rating": 5,
      "type": "Management"
    },
    "normJobTitle": "30 лет",
    "overallRating": 5,
    "redacted": false,
    "reviewUid": "1f12eqrvi3jl2000",
    "reviewUrl": "/cmp/%D0%9E%D0%B0%D0%BE-%22%D1%80%D0%B6%D0%B4%22/reviews/%D0%BE%D1%82%D0%B2%D0%B5%D1%82%D1%81%D1%82%D0%B2%D0%B5%D0%BD%D0%BD%D0%B0%D1%8F-%D0%B8%D0%BD%D1%82%D0%B5%D1%80%D0%B5%D1%81%D0%BD%D0%B0%D1%8F-%D1%80%D0%B0%D0%B1%D0%BE%D1%82%D0%B0?id=75ec9a09e9202e57",
    "sharingLink": "https://www.indeed.com/cmp/%D0%9E%D0%B0%D0%BE-%22%D1%80%D0%B6%D0%B4%22/reviews/%D0%BE%D1%82%D0%B2%D0%B5%D1%82%D1%81%D1%82%D0%B2%D0%B5%D0%BD%D0%BD%D0%B0%D1%8F-%D0%B8%D0%BD%D1%82%D0%B5%D1%80%D0%B5%D1%81%D0%BD%D0%B0%D1%8F-%D1%80%D0%B0%D0%B1%D0%BE%D1%82%D0%B0?id=75ec9a09e9202e57",
    "submissionDate": "March 18, 2021",
    "text": {
      "languageTag": "ru-RU",
      "text": "Я горжусь своей профессией и всем советую работу на РЖЖ"
    },
    "title": {
      "languageTag": "ru-RU",
      "text": "Ответственная интересная работа "
    },
    "tweetAutoFillText": "ОАО \"РЖД\" review on #indeedjobs: \"Ответственная интересная работа \"",
    "type": "LIST",
    "unhelpful": 5,
    "workAndLifeBalanceRating": {
      "rating": 5,
      "type": "Job Work/Life Balance"
    }
  },
  {
    "comments": [],
    "compensationAndBenefitsRating": {
      "rating": 4,
      "type": "Compensation/Benefits"
    },
    "cons": {
      "languageTag": "ru-RU",
      "text": "Стресс"
    },
    "country": "RU",
    "cultureAndValuesRating": {
      "rating": 1,
      "type": "Job Culture"
    },
    "currentEmployee": false,
    "encryptedReviewId": "7349c04db1ba6f1d",
    "headerTitle": "ОАО \"РЖД\" Распределитель работ Review - Работа, полная стрессов",
    "helpful": 1,
    "indexable": false,
    "isDeletable": false,
    "jobSecurityAndAdvancementRating": {
      "rating": 4,
      "type": "Job Security/Advancement"
    },
    "jobTitle": "Распределитель работ",
    "jobTitleFilterLink": "/cmp/%D0%9E%D0%B0%D0%BE-%22%D1%80%D0%B6%D0%B4%22/reviews?fjobtitle=%D0%A0%D0%B0%D1%81%D0%BF%D1%80%D0%B5%D0%B4%D0%B5%D0%BB%D0%B8%D1%82%D0%B5%D0%BB%D1%8C+%D1%80%D0%B0%D0%B1%D0%BE%D1%82",
    "location": "Новокузнецк",
    "locationFilterLink": "/cmp/%D0%9E%D0%B0%D0%BE-%22%D1%80%D0%B6%D0%B4%22/reviews?fcountry=RU&floc=%D0%9D%D0%BE%D0%B2%D0%BE%D0%BA%D1%83%D0%B7%D0%BD%D0%B5%D1%86%D0%BA",
    "managementRating": {
      "rating": 1,
      "type": "Management"
    },
    "normJobTitle": "Распределитель работ",
    "overallRating": 3,
    "pros": {
      "languageTag": "ru-RU",
      "text": "Зарплаты"
    },
    "redacted": false,
    "reviewUid": "1eu4sk5e6stvb800",
    "reviewUrl": "/cmp/%D0%9E%D0%B0%D0%BE-%22%D1%80%D0%B6%D0%B4%22/reviews/%D1%80%D0%B0%D0%B1%D0%BE%D1%82%D0%B0-%D0%BF%D0%BE%D0%BB%D0%BD%D0%B0%D1%8F-%D1%81%D1%82%D1%80%D0%B5%D1%81%D1%81%D0%BE%D0%B2?id=7349c04db1ba6f1d",
    "sharingLink": "https://www.indeed.com/cmp/%D0%9E%D0%B0%D0%BE-%22%D1%80%D0%B6%D0%B4%22/reviews/%D1%80%D0%B0%D0%B1%D0%BE%D1%82%D0%B0-%D0%BF%D0%BE%D0%BB%D0%BD%D0%B0%D1%8F-%D1%81%D1%82%D1%80%D0%B5%D1%81%D1%81%D0%BE%D0%B2?id=7349c04db1ba6f1d",
    "submissionDate": "February 9, 2021",
    "text": {
      "languageTag": "ru-RU",
      "text": "Из-за чего стоит работать на ОАО РЖД, так это из-за достойной зарплаты. "
    },
    "title": {
      "languageTag": "ru-RU",
      "text": "Работа, полная стрессов"
    },
    "tweetAutoFillText": "ОАО \"РЖД\" review on #indeedjobs: \"Работа, полная стрессов\"",
    "type": "LIST",
    "unhelpful": 2,
    "workAndLifeBalanceRating": {
      "rating": 3,
      "type": "Job Work/Life Balance"
    }
  },
  {
    "comments": [],
    "compensationAndBenefitsRating": {
      "rating": 2,
      "type": "Compensation/Benefits"
    },
    "cons": {
      "languageTag": "ru-RU",
      "text": "Нет графика, мало выходных, постоянные сверх урочные, постоянно грабят путем лишения премии."
    },
    "country": "RU",
    "cultureAndValuesRating": {
      "rating": 2,
      "type": "Job Culture"
    },
    "currentEmployee": false,
    "encryptedReviewId": "d36823b043da6d73",
    "headerTitle": "ОАО \"РЖД\" Машинист тепловоза Review - Работа тяжелая, зарплата не высокая",
    "helpful": 8,
    "indexable": true,
    "isDeletable": false,
    "jobSecurityAndAdvancementRating": {
      "rating": 5,
      "type": "Job Security/Advancement"
    },
    "jobTitle": "Машинист тепловоза",
    "jobTitleFilterLink": "/cmp/%D0%9E%D0%B0%D0%BE-%22%D1%80%D0%B6%D0%B4%22/reviews?fjobtitle=%D0%9C%D0%B0%D1%88%D0%B8%D0%BD%D0%B8%D1%81%D1%82+%D0%94%D0%BE%D1%80%D0%BE%D0%B6%D0%BD%D0%BE-%D1%82%D1%80%D0%B0%D0%BD%D1%81%D0%BF%D0%BE%D1%80%D1%82%D0%BD%D1%8B%D1%85+%D0%9C%D0%B0%D1%88%D0%B8%D0%BD",
    "location": "Оборотное депо Рыбинск, эксплуатационного локомотивного депо Иваново",
    "locationFilterLink": "/cmp/%D0%9E%D0%B0%D0%BE-%22%D1%80%D0%B6%D0%B4%22/reviews?fcountry=RU&floc=%D0%98%D0%B2%D0%B0%D0%BD%D0%BE%D0%B2%D0%BE",
    "managementRating": {
      "rating": 1,
      "type": "Management"
    },
    "normJobTitle": "Машинист Дорожно-транспортных Машин",
    "overallRating": 1,
    "pros": {
      "languageTag": "ru-RU",
      "text": "Бесплатный проезд в пригороде, удержат подоходный все равно."
    },
    "redacted": false,
    "reviewUid": "1etu98vnp3jna000",
    "reviewUrl": "/cmp/%D0%9E%D0%B0%D0%BE-%22%D1%80%D0%B6%D0%B4%22/reviews/%D1%80%D0%B0%D0%B1%D0%BE%D1%82%D0%B0-%D1%82%D1%8F%D0%B6%D0%B5%D0%BB%D0%B0%D1%8F-%D0%B7%D0%B0%D1%80%D0%BF%D0%BB%D0%B0%D1%82%D0%B0-%D0%BD%D0%B5-%D0%B2%D1%8B%D1%81%D0%BE%D0%BA%D0%B0%D1%8F?id=d36823b043da6d73",
    "sharingLink": "https://www.indeed.com/cmp/%D0%9E%D0%B0%D0%BE-%22%D1%80%D0%B6%D0%B4%22/reviews/%D1%80%D0%B0%D0%B1%D0%BE%D1%82%D0%B0-%D1%82%D1%8F%D0%B6%D0%B5%D0%BB%D0%B0%D1%8F-%D0%B7%D0%B0%D1%80%D0%BF%D0%BB%D0%B0%D1%82%D0%B0-%D0%BD%D0%B5-%D0%B2%D1%8B%D1%81%D0%BE%D0%BA%D0%B0%D1%8F?id=d36823b043da6d73",
    "submissionDate": "February 7, 2021",
    "text": {
      "languageTag": "ru-RU",
      "text": "Если вам нравится работа по ночам, полное отсутствие графика,  постоянные стрессы, отношение к людям как к скотине, постоянные лишения премии из за пустяков, придирки со стороны начальства, мазута, ДИКИЙ ШУМ, вонь солярки, летом нестерпимая жара, зимой дубак, медкомиссия как на космонафта (непрошол - списали), посещение в свое свободное время тех-учебы и выполнение различных компьютерных тестов, не фиксированное рабочее время (можно проездить и сутки и двое) то есть дома вы будете бывать совсем редко, и все это за скромную зарплату: помошник около 30 000, машинист около 40 000 то вам в ОАО РЖД !!!!!"
    },
    "title": {
      "languageTag": "ru-RU",
      "text": "Работа тяжелая, зарплата не высокая"
    },
    "tweetAutoFillText": "ОАО \"РЖД\" review on #indeedjobs: \"Работа тяжелая, зарплата не высокая\"",
    "type": "LIST",
    "unhelpful": 0,
    "workAndLifeBalanceRating": {
      "rating": 5,
      "type": "Job Work/Life Balance"
    }
  },
  {
    "comments": [],
    "compensationAndBenefitsRating": {
      "rating": 4,
      "type": "Compensation/Benefits"
    },
    "country": "RU",
    "cultureAndValuesRating": {
      "rating": 5,
      "type": "Job Culture"
    },
    "currentEmployee": true,
    "encryptedReviewId": "56bd14921eb1c895",
    "headerTitle": "ОАО \"РЖД\" Дежурный по железнодорожной станции Review - Продуктивная и напряжённая работа дсп",
    "helpful": 0,
    "indexable": false,
    "isDeletable": false,
    "jobSecurityAndAdvancementRating": {
      "rating": 4,
      "type": "Job Security/Advancement"
    },
    "jobTitle": "Дежурный по железнодорожной станции",
    "jobTitleFilterLink": "/cmp/%D0%9E%D0%B0%D0%BE-%22%D1%80%D0%B6%D0%B4%22/reviews?fjobtitle=%D0%94%D0%B5%D0%B6%D1%83%D1%80%D0%BD%D1%8B%D0%B9",
    "location": "Ст. Парма",
    "managementRating": {
      "rating": 3,
      "type": "Management"
    },
    "normJobTitle": "Дежурный",
    "overallRating": 4,
    "pros": {
      "languageTag": "ru-RU",
      "text": "Бесплатный проезд"
    },
    "redacted": false,
    "reviewUid": "1esd3v4esstqg800",
    "reviewUrl": "/cmp/%D0%9E%D0%B0%D0%BE-%22%D1%80%D0%B6%D0%B4%22/reviews/%D0%BF%D1%80%D0%BE%D0%B4%D1%83%D0%BA%D1%82%D0%B8%D0%B2%D0%BD%D0%B0%D1%8F-%D0%B8-%D0%BD%D0%B0%D0%BF%D1%80%D1%8F%D0%B6%D1%91%D0%BD%D0%BD%D0%B0%D1%8F-%D1%80%D0%B0%D0%B1%D0%BE%D1%82%D0%B0-%D0%B4%D1%81%D0%BF?id=56bd14921eb1c895",
    "sharingLink": "https://www.indeed.com/cmp/%D0%9E%D0%B0%D0%BE-%22%D1%80%D0%B6%D0%B4%22/reviews/%D0%BF%D1%80%D0%BE%D0%B4%D1%83%D0%BA%D1%82%D0%B8%D0%B2%D0%BD%D0%B0%D1%8F-%D0%B8-%D0%BD%D0%B0%D0%BF%D1%80%D1%8F%D0%B6%D1%91%D0%BD%D0%BD%D0%B0%D1%8F-%D1%80%D0%B0%D0%B1%D0%BE%D1%82%D0%B0-%D0%B4%D1%81%D0%BF?id=56bd14921eb1c895",
    "submissionDate": "January 19, 2021",
    "text": {
      "languageTag": "ru-RU",
      "text": "Заработная плата соответствует требованиям предьявляемым к работнику. "
    },
    "title": {
      "languageTag": "ru-RU",
      "text": "Продуктивная и напряжённая работа дсп"
    },
    "tweetAutoFillText": "ОАО \"РЖД\" review on #indeedjobs: \"Продуктивная и напряжённая работа дсп\"",
    "type": "LIST",
    "unhelpful": 0,
    "workAndLifeBalanceRating": {
      "rating": 4,
      "type": "Job Work/Life Balance"
    }
  },
  {
    "comments": [],
    "compensationAndBenefitsRating": {
      "rating": 4,
      "type": "Compensation/Benefits"
    },
    "country": "RU",
    "cultureAndValuesRating": {
      "rating": 4,
      "type": "Job Culture"
    },
    "currentEmployee": true,
    "encryptedReviewId": "bdbf0db41eec0f56",
    "headerTitle": "ОАО \"РЖД\" проводник Review - оплата хорошая и вовремя",
    "helpful": 0,
    "indexable": false,
    "isDeletable": false,
    "jobSecurityAndAdvancementRating": {
      "rating": 4,
      "type": "Job Security/Advancement"
    },
    "jobTitle": "проводник",
    "jobTitleFilterLink": "/cmp/%D0%9E%D0%B0%D0%BE-%22%D1%80%D0%B6%D0%B4%22/reviews?fjobtitle=%D0%BF%D1%80%D0%BE%D0%B2%D0%BE%D0%B4%D0%BD%D0%B8%D0%BA",
    "location": "Москва",
    "locationFilterLink": "/cmp/%D0%9E%D0%B0%D0%BE-%22%D1%80%D0%B6%D0%B4%22/reviews?fcountry=RU&floc=%D0%9C%D0%BE%D1%81%D0%BA%D0%B2%D0%B0",
    "managementRating": {
      "rating": 4,
      "type": "Management"
    },
    "normJobTitle": "проводник",
    "overallRating": 4,
    "pros": {
      "languageTag": "ru-RU",
      "text": "соцпакет"
    },
    "redacted": false,
    "reviewUid": "1epgbqabk3jlo000",
    "reviewUrl": "/cmp/%D0%9E%D0%B0%D0%BE-%22%D1%80%D0%B6%D0%B4%22/reviews/%D0%BE%D0%BF%D0%BB%D0%B0%D1%82%D0%B0-%D1%85%D0%BE%D1%80%D0%BE%D1%88%D0%B0%D1%8F-%D0%B8-%D0%B2%D0%BE%D0%B2%D1%80%D0%B5%D0%BC%D1%8F?id=bdbf0db41eec0f56",
    "sharingLink": "https://www.indeed.com/cmp/%D0%9E%D0%B0%D0%BE-%22%D1%80%D0%B6%D0%B4%22/reviews/%D0%BE%D0%BF%D0%BB%D0%B0%D1%82%D0%B0-%D1%85%D0%BE%D1%80%D0%BE%D1%88%D0%B0%D1%8F-%D0%B8-%D0%B2%D0%BE%D0%B2%D1%80%D0%B5%D0%BC%D1%8F?id=bdbf0db41eec0f56",
    "submissionDate": "December 14, 2020",
    "text": {
      "languageTag": "ru-RU",
      "text": "Я не особо общаюсь с руководством, поэтому у меня к ним и нет никаких претензий. Главное, на мой взгляд, чтобы работа была, выполнялась в срок и за это оплачивали хорошо и вовремя. Из доп.плюсов - соц.пакета, такой еще и поискать..."
    },
    "title": {
      "languageTag": "ru-RU",
      "text": "оплата хорошая и вовремя"
    },
    "tweetAutoFillText": "ОАО \"РЖД\" review on #indeedjobs: \"оплата хорошая и вовремя\"",
    "type": "LIST",
    "unhelpful": 0,
    "workAndLifeBalanceRating": {
      "rating": 4,
      "type": "Job Work/Life Balance"
    }
  },
  {
    "comments": [],
    "compensationAndBenefitsRating": {
      "rating": 5,
      "type": "Compensation/Benefits"
    },
    "cons": {
      "languageTag": "ru-RU",
      "text": "конкуренция"
    },
    "country": "RU",
    "cultureAndValuesRating": {
      "rating": 5,
      "type": "Job Culture"
    },
    "currentEmployee": true,
    "encryptedReviewId": "d30aa9d95143b8c6",
    "headerTitle": "ОАО \"РЖД\" мастер Review - нормальная работа",
    "helpful": 0,
    "indexable": false,
    "isDeletable": false,
    "jobSecurityAndAdvancementRating": {
      "rating": 5,
      "type": "Job Security/Advancement"
    },
    "jobTitle": "мастер",
    "jobTitleFilterLink": "/cmp/%D0%9E%D0%B0%D0%BE-%22%D1%80%D0%B6%D0%B4%22/reviews?fjobtitle=%D0%9C%D0%B0%D1%81%D1%82%D0%B5%D1%80",
    "location": "Москва",
    "locationFilterLink": "/cmp/%D0%9E%D0%B0%D0%BE-%22%D1%80%D0%B6%D0%B4%22/reviews?fcountry=RU&floc=%D0%9C%D0%BE%D1%81%D0%BA%D0%B2%D0%B0",
    "managementRating": {
      "rating": 5,
      "type": "Management"
    },
    "normJobTitle": "Мастер",
    "overallRating": 5,
    "pros": {
      "languageTag": "ru-RU",
      "text": "нормальная работа"
    },
    "redacted": false,
    "reviewUid": "1ep3frk6jssm8800",
    "reviewUrl": "/cmp/%D0%9E%D0%B0%D0%BE-%22%D1%80%D0%B6%D0%B4%22/reviews/%D0%BD%D0%BE%D1%80%D0%BC%D0%B0%D0%BB%D1%8C%D0%BD%D0%B0%D1%8F-%D1%80%D0%B0%D0%B1%D0%BE%D1%82%D0%B0?id=d30aa9d95143b8c6",
    "sharingLink": "https://www.indeed.com/cmp/%D0%9E%D0%B0%D0%BE-%22%D1%80%D0%B6%D0%B4%22/reviews/%D0%BD%D0%BE%D1%80%D0%BC%D0%B0%D0%BB%D1%8C%D0%BD%D0%B0%D1%8F-%D1%80%D0%B0%D0%B1%D0%BE%D1%82%D0%B0?id=d30aa9d95143b8c6",
    "submissionDate": "December 9, 2020",
    "text": {
      "languageTag": "ru-RU",
      "text": "Если выкладываться на работе на 100 процентов и не зубоскалить с начальством, то и на зп это отражается в лучшую сторону и вполне можно пойти вверх по карьерной лестнице. Большая компания, желающих много расти вверх, а достойны не все, поэтому и конкуренция"
    },
    "title": {
      "languageTag": "ru-RU",
      "text": "нормальная работа"
    },
    "tweetAutoFillText": "ОАО \"РЖД\" review on #indeedjobs: \"нормальная работа\"",
    "type": "LIST",
    "unhelpful": 1,
    "workAndLifeBalanceRating": {
      "rating": 5,
      "type": "Job Work/Life Balance"
    }
  },
  {
    "comments": [],
    "compensationAndBenefitsRating": {
      "rating": 3,
      "type": "Compensation/Benefits"
    },
    "cons": {
      "languageTag": "ru-RU",
      "text": "Плохая медицина и коррупция"
    },
    "country": "RU",
    "cultureAndValuesRating": {
      "rating": 5,
      "type": "Job Culture"
    },
    "currentEmployee": false,
    "encryptedReviewId": "26de3a97132e27d3",
    "headerTitle": "ОАО \"РЖД\" Дежурный по переезду Review - Нет",
    "helpful": 1,
    "indexable": false,
    "isDeletable": false,
    "jobSecurityAndAdvancementRating": {
      "rating": 4,
      "type": "Job Security/Advancement"
    },
    "jobTitle": "Дежурный по переезду",
    "jobTitleFilterLink": "/cmp/%D0%9E%D0%B0%D0%BE-%22%D1%80%D0%B6%D0%B4%22/reviews?fjobtitle=%D0%94%D0%B5%D0%B6%D1%83%D1%80%D0%BD%D1%8B%D0%B9",
    "location": "Спмс ",
    "managementRating": {
      "rating": 2,
      "type": "Management"
    },
    "normJobTitle": "Дежурный",
    "overallRating": 3,
    "pros": {
      "languageTag": "ru-RU",
      "text": "Оплата выслуги лет"
    },
    "redacted": false,
    "reviewUid": "1el1abd78std5800",
    "reviewUrl": "/cmp/%D0%9E%D0%B0%D0%BE-%22%D1%80%D0%B6%D0%B4%22/reviews/%D0%BD%D0%B5%D1%82?id=26de3a97132e27d3",
    "sharingLink": "https://www.indeed.com/cmp/%D0%9E%D0%B0%D0%BE-%22%D1%80%D0%B6%D0%B4%22/reviews/%D0%BD%D0%B5%D1%82?id=26de3a97132e27d3",
    "submissionDate": "October 19, 2020",
    "text": {
      "languageTag": "ru-RU",
      "text": "Ужасная компания плохие условия труда для рабочего цеха "
    },
    "title": {
      "languageTag": "ru-RU",
      "text": "Нет"
    },
    "tweetAutoFillText": "ОАО \"РЖД\" review on #indeedjobs: \"Нет\"",
    "type": "LIST",
    "unhelpful": 0,
    "workAndLifeBalanceRating": {
      "rating": 3,
      "type": "Job Work/Life Balance"
    }
  },
  {
    "comments": [],
    "compensationAndBenefitsRating": {
      "rating": 1,
      "type": "Compensation/Benefits"
    },
    "cons": {
      "languageTag": "ru-RU",
      "text": "все"
    },
    "country": "RU",
    "cultureAndValuesRating": {
      "rating": 1,
      "type": "Job Culture"
    },
    "currentEmployee": false,
    "encryptedReviewId": "3f507a5bed4b2886",
    "headerTitle": "ОАО \"РЖД\" МАНТЕР ПУТИ Review - ужасная компания! не кому не советую!!!",
    "helpful": 1,
    "indexable": false,
    "isDeletable": false,
    "jobSecurityAndAdvancementRating": {
      "rating": 1,
      "type": "Job Security/Advancement"
    },
    "jobTitle": "МАНТЕР ПУТИ",
    "jobTitleFilterLink": "/cmp/%D0%9E%D0%B0%D0%BE-%22%D1%80%D0%B6%D0%B4%22/reviews?fjobtitle=%D0%9C%D0%90%D0%9D%D0%A2%D0%95%D0%A0+%D0%9F%D0%A3%D0%A2%D0%98",
    "location": "пч 4 город Зима",
    "locationFilterLink": "/cmp/%D0%9E%D0%B0%D0%BE-%22%D1%80%D0%B6%D0%B4%22/reviews?fcountry=RU&floc=%D0%97%D0%B8%D0%BC%D0%B0",
    "managementRating": {
      "rating": 1,
      "type": "Management"
    },
    "normJobTitle": "МАНТЕР ПУТИ",
    "overallRating": 1,
    "pros": {
      "languageTag": "ru-RU",
      "text": "нет"
    },
    "redacted": false,
    "reviewUid": "1ekj6ouhnsta4800",
    "reviewUrl": "/cmp/%D0%9E%D0%B0%D0%BE-%22%D1%80%D0%B6%D0%B4%22/reviews/%D1%83%D0%B6%D0%B0%D1%81%D0%BD%D0%B0%D1%8F-%D0%BA%D0%BE%D0%BC%D0%BF%D0%B0%D0%BD%D0%B8%D1%8F-%D0%BD%D0%B5-%D0%BA%D0%BE%D0%BC%D1%83-%D0%BD%D0%B5-%D1%81%D0%BE%D0%B2%D0%B5%D1%82%D1%83%D1%8E?id=3f507a5bed4b2886",
    "sharingLink": "https://www.indeed.com/cmp/%D0%9E%D0%B0%D0%BE-%22%D1%80%D0%B6%D0%B4%22/reviews/%D1%83%D0%B6%D0%B0%D1%81%D0%BD%D0%B0%D1%8F-%D0%BA%D0%BE%D0%BC%D0%BF%D0%B0%D0%BD%D0%B8%D1%8F-%D0%BD%D0%B5-%D0%BA%D0%BE%D0%BC%D1%83-%D0%BD%D0%B5-%D1%81%D0%BE%D0%B2%D0%B5%D1%82%D1%83%D1%8E?id=3f507a5bed4b2886",
    "submissionDate": "October 14, 2020",
    "text": {
      "languageTag": "ru-RU",
      "text": "Ужасное отношение к рабочей силе.\nПолучил производственную травму не какой поддержке не материальной не какой. только палки в колеса. \n"
    },
    "title": {
      "languageTag": "ru-RU",
      "text": "ужасная компания! не кому не советую!!!"
    },
    "tweetAutoFillText": "ОАО \"РЖД\" review on #indeedjobs: \"ужасная компания! не кому не советую!!!\"",
    "type": "LIST",
    "unhelpful": 0,
    "workAndLifeBalanceRating": {
      "rating": 1,
      "type": "Job Work/Life Balance"
    }
  },
  {
    "comments": [],
    "compensationAndBenefitsRating": {
      "rating": 4,
      "type": "Compensation/Benefits"
    },
    "cons": {
      "languageTag": "ru-RU",
      "text": "Работа в выходные"
    },
    "country": "RU",
    "cultureAndValuesRating": {
      "rating": 5,
      "type": "Job Culture"
    },
    "currentEmployee": false,
    "encryptedReviewId": "d2d7b37f5bede9d0",
    "headerTitle": "ОАО \"РЖД\" Приемщик поездов Review - Хорошая компания",
    "helpful": 0,
    "indexable": false,
    "isDeletable": false,
    "jobSecurityAndAdvancementRating": {
      "rating": 5,
      "type": "Job Security/Advancement"
    },
    "jobTitle": "Приемщик поездов",
    "jobTitleFilterLink": "/cmp/%D0%9E%D0%B0%D0%BE-%22%D1%80%D0%B6%D0%B4%22/reviews?fjobtitle=%D0%9F%D1%80%D0%B8%D1%91%D0%BC%D1%89%D0%B8%D0%BA",
    "location": "Иркутск",
    "locationFilterLink": "/cmp/%D0%9E%D0%B0%D0%BE-%22%D1%80%D0%B6%D0%B4%22/reviews?fcountry=RU&floc=%D0%98%D1%80%D0%BA%D1%83%D1%82%D1%81%D0%BA",
    "managementRating": {
      "rating": 5,
      "type": "Management"
    },
    "normJobTitle": "Приёмщик",
    "overallRating": 5,
    "pros": {
      "languageTag": "ru-RU",
      "text": "Карьерный рост"
    },
    "redacted": false,
    "reviewUid": "1ejkqsoia3jg0000",
    "reviewUrl": "/cmp/%D0%9E%D0%B0%D0%BE-%22%D1%80%D0%B6%D0%B4%22/reviews/%D1%85%D0%BE%D1%80%D0%BE%D1%88%D0%B0%D1%8F-%D0%BA%D0%BE%D0%BC%D0%BF%D0%B0%D0%BD%D0%B8%D1%8F?id=d2d7b37f5bede9d0",
    "sharingLink": "https://www.indeed.com/cmp/%D0%9E%D0%B0%D0%BE-%22%D1%80%D0%B6%D0%B4%22/reviews/%D1%85%D0%BE%D1%80%D0%BE%D1%88%D0%B0%D1%8F-%D0%BA%D0%BE%D0%BC%D0%BF%D0%B0%D0%BD%D0%B8%D1%8F?id=d2d7b37f5bede9d0",
    "submissionDate": "October 2, 2020",
    "text": {
      "languageTag": "ru-RU",
      "text": "Работа в РЖД очень престижно и интересно. Отличная,стабильная организация. С карьерным ростом и хорошим коллективом. Начальство отличное,всегда найдет компромисс во всем. Процветающая организация. Я была очень довольна,работая в ОАО РЖД."
    },
    "title": {
      "languageTag": "ru-RU",
      "text": "Хорошая компания"
    },
    "tweetAutoFillText": "ОАО \"РЖД\" review on #indeedjobs: \"Хорошая компания\"",
    "type": "LIST",
    "unhelpful": 1,
    "workAndLifeBalanceRating": {
      "rating": 3,
      "type": "Job Work/Life Balance"
    }
  },
  {
    "comments": [],
    "compensationAndBenefitsRating": {
      "rating": 1,
      "type": "Compensation/Benefits"
    },
    "cons": {
      "languageTag": "ru-RU",
      "text": "Ухудшение здоровья"
    },
    "country": "RU",
    "cultureAndValuesRating": {
      "rating": 1,
      "type": "Job Culture"
    },
    "currentEmployee": false,
    "encryptedReviewId": "37aff28785c5d60c",
    "headerTitle": "ОАО \"РЖД\" Руководитель техотдела Review - Полная жесть",
    "helpful": 0,
    "indexable": false,
    "isDeletable": false,
    "jobSecurityAndAdvancementRating": {
      "rating": 1,
      "type": "Job Security/Advancement"
    },
    "jobTitle": "Руководитель техотдела",
    "jobTitleFilterLink": "/cmp/%D0%9E%D0%B0%D0%BE-%22%D1%80%D0%B6%D0%B4%22/reviews?fjobtitle=%D0%A0%D1%83%D0%BA%D0%BE%D0%B2%D0%BE%D0%B4%D0%B8%D1%82%D0%B5%D0%BB%D1%8C",
    "location": "Москва",
    "locationFilterLink": "/cmp/%D0%9E%D0%B0%D0%BE-%22%D1%80%D0%B6%D0%B4%22/reviews?fcountry=RU&floc=%D0%9C%D0%BE%D1%81%D0%BA%D0%B2%D0%B0",
    "managementRating": {
      "rating": 1,
      "type": "Management"
    },
    "normJobTitle": "Руководитель",
    "overallRating": 1,
    "pros": {
      "languageTag": "ru-RU",
      "text": "Призвание"
    },
    "redacted": false,
    "reviewUid": "1eivgjakq3jl2000",
    "reviewUrl": "/cmp/%D0%9E%D0%B0%D0%BE-%22%D1%80%D0%B6%D0%B4%22/reviews/%D0%BF%D0%BE%D0%BB%D0%BD%D0%B0%D1%8F-%D0%B6%D0%B5%D1%81%D1%82%D1%8C?id=37aff28785c5d60c",
    "sharingLink": "https://www.indeed.com/cmp/%D0%9E%D0%B0%D0%BE-%22%D1%80%D0%B6%D0%B4%22/reviews/%D0%BF%D0%BE%D0%BB%D0%BD%D0%B0%D1%8F-%D0%B6%D0%B5%D1%81%D1%82%D1%8C?id=37aff28785c5d60c",
    "submissionDate": "September 24, 2020",
    "text": {
      "languageTag": "ru-RU",
      "text": "Рвать Ж..пу Даром или работать чем дольше и при этом ничего не получать"
    },
    "title": {
      "languageTag": "ru-RU",
      "text": "Полная жесть"
    },
    "tweetAutoFillText": "ОАО \"РЖД\" review on #indeedjobs: \"Полная жесть\"",
    "type": "LIST",
    "unhelpful": 0,
    "workAndLifeBalanceRating": {
      "rating": 1,
      "type": "Job Work/Life Balance"
    }
  },
  {
    "comments": [],
    "compensationAndBenefitsRating": {
      "rating": 4,
      "type": "Compensation/Benefits"
    },
    "cons": {
      "languageTag": "ru-RU",
      "text": "Работа разнорабочим, не по специальности, небольшая зарплата, долгое ожидание при оформлении на работу."
    },
    "country": "RU",
    "cultureAndValuesRating": {
      "rating": 2,
      "type": "Job Culture"
    },
    "currentEmployee": false,
    "encryptedReviewId": "8fdcaf36f4f23de0",
    "headerTitle": "ОАО \"РЖД\" Слесарь-сантехник Review - Работа не соответствует должностной инструкции",
    "helpful": 0,
    "indexable": true,
    "isDeletable": false,
    "jobSecurityAndAdvancementRating": {
      "rating": 1,
      "type": "Job Security/Advancement"
    },
    "jobTitle": "Слесарь-сантехник",
    "jobTitleFilterLink": "/cmp/%D0%9E%D0%B0%D0%BE-%22%D1%80%D0%B6%D0%B4%22/reviews?fjobtitle=%D0%A1%D0%BB%D0%B5%D1%81%D0%B0%D1%80%D1%8C-%D1%81%D0%B0%D0%BD%D1%82%D0%B5%D1%85%D0%BD%D0%B8%D0%BA",
    "location": "Железнодорожный вокзал г.Уфы",
    "locationFilterLink": "/cmp/%D0%9E%D0%B0%D0%BE-%22%D1%80%D0%B6%D0%B4%22/reviews?fcountry=RU&floc=%D0%96%D0%B5%D0%BB%D0%B5%D0%B7%D0%BD%D0%BE%D0%B4%D0%BE%D1%80%D0%BE%D0%B6%D0%BD%D1%8B%D0%B9",
    "managementRating": {
      "rating": 4,
      "type": "Management"
    },
    "normJobTitle": "Слесарь-сантехник",
    "overallRating": 3,
    "pros": {
      "languageTag": "ru-RU",
      "text": "Бесплатный проезд на электричке, своевременная зарплата"
    },
    "redacted": false,
    "reviewUid": "1efbur8dkq2ll800",
    "reviewUrl": "/cmp/%D0%9E%D0%B0%D0%BE-%22%D1%80%D0%B6%D0%B4%22/reviews/%D1%80%D0%B0%D0%B1%D0%BE%D1%82%D0%B0-%D0%BD%D0%B5-%D1%81%D0%BE%D0%BE%D1%82%D0%B2%D0%B5%D1%82%D1%81%D1%82%D0%B2%D1%83%D0%B5%D1%82-%D0%B4%D0%BE%D0%BB%D0%B6%D0%BD%D0%BE%D1%81%D1%82%D0%BD%D0%BE%D0%B9-%D0%B8%D0%BD%D1%81%D1%82%D1%80%D1%83%D0%BA%D1%86%D0%B8%D0%B8?id=8fdcaf36f4f23de0",
    "sharingLink": "https://www.indeed.com/cmp/%D0%9E%D0%B0%D0%BE-%22%D1%80%D0%B6%D0%B4%22/reviews/%D1%80%D0%B0%D0%B1%D0%BE%D1%82%D0%B0-%D0%BD%D0%B5-%D1%81%D0%BE%D0%BE%D1%82%D0%B2%D0%B5%D1%82%D1%81%D1%82%D0%B2%D1%83%D0%B5%D1%82-%D0%B4%D0%BE%D0%BB%D0%B6%D0%BD%D0%BE%D1%81%D1%82%D0%BD%D0%BE%D0%B9-%D0%B8%D0%BD%D1%81%D1%82%D1%80%D1%83%D0%BA%D1%86%D0%B8%D0%B8?id=8fdcaf36f4f23de0",
    "submissionDate": "August 10, 2020",
    "text": {
      "languageTag": "ru-RU",
      "text": "Был на собеседовании при устройстве на вакансию слесаря-сантехника 4 разряда.непосредственный руководитель ознакомился с документами и подробно рассказал про обязанности слесаря-сантехника.Работа в комплексной бригаде из трех специалистов,как видно из названия комплексной бригады,все в бригаде выполняют работы,которые даже не положено выполнять по своей должности.Руководитель объяснил это тем,что не хватает работников,поэтому все работники выполняют те работы,которые появляются,то есть все от обслуживания до строительно-погрузочных работ.Поэтому не удивительно,что на вакансии электромонтера и слесаря-сантехника никто не устраивается.В течение дня постоянно объявляют по радио на вокзале,что есть вакансии на электромонтера и слесаря-сантехника.Лучше бы назвали вакансию РАЗНОРАБОЧИМ,это было бы правильней,чем говорить и писать неправду!Если хочется кому то приключений,то вам сюда!!!"
    },
    "title": {
      "languageTag": "ru-RU",
      "text": "Работа не соответствует должностной инструкции"
    },
    "tweetAutoFillText": "ОАО \"РЖД\" review on #indeedjobs: \"Работа не соответствует должностной инструкции\"",
    "type": "LIST",
    "unhelpful": 1,
    "workAndLifeBalanceRating": {
      "rating": 1,
      "type": "Job Work/Life Balance"
    }
  },
  {
    "comments": [],
    "compensationAndBenefitsRating": {
      "rating": 2,
      "type": "Compensation/Benefits"
    },
    "country": "RU",
    "cultureAndValuesRating": {
      "rating": 4,
      "type": "Job Culture"
    },
    "currentEmployee": false,
    "encryptedReviewId": "0de006dd11bebf27",
    "headerTitle": "ОАО \"РЖД\" мастер Review - Типичный день на работе",
    "helpful": 0,
    "indexable": false,
    "isDeletable": false,
    "jobSecurityAndAdvancementRating": {
      "rating": 2,
      "type": "Job Security/Advancement"
    },
    "jobTitle": "мастер",
    "jobTitleFilterLink": "/cmp/%D0%9E%D0%B0%D0%BE-%22%D1%80%D0%B6%D0%B4%22/reviews?fjobtitle=%D0%9C%D0%B0%D1%81%D1%82%D0%B5%D1%80",
    "location": "Абакан",
    "locationFilterLink": "/cmp/%D0%9E%D0%B0%D0%BE-%22%D1%80%D0%B6%D0%B4%22/reviews?fcountry=RU&floc=%D0%90%D0%B1%D0%B0%D0%BA%D0%B0%D0%BD",
    "managementRating": {
      "rating": 2,
      "type": "Management"
    },
    "normJobTitle": "Мастер",
    "overallRating": 3,
    "redacted": false,
    "reviewUid": "1ee83h8c5r7lv800",
    "reviewUrl": "/cmp/%D0%9E%D0%B0%D0%BE-%22%D1%80%D0%B6%D0%B4%22/reviews/%D1%82%D0%B8%D0%BF%D0%B8%D1%87%D0%BD%D1%8B%D0%B9-%D0%B4%D0%B5%D0%BD%D1%8C-%D0%BD%D0%B0-%D1%80%D0%B0%D0%B1%D0%BE%D1%82%D0%B5?id=0de006dd11bebf27",
    "sharingLink": "https://www.indeed.com/cmp/%D0%9E%D0%B0%D0%BE-%22%D1%80%D0%B6%D0%B4%22/reviews/%D1%82%D0%B8%D0%BF%D0%B8%D1%87%D0%BD%D1%8B%D0%B9-%D0%B4%D0%B5%D0%BD%D1%8C-%D0%BD%D0%B0-%D1%80%D0%B0%D0%B1%D0%BE%D1%82%D0%B5?id=0de006dd11bebf27",
    "submissionDate": "July 27, 2020",
    "text": {
      "languageTag": "ru-RU",
      "text": "Много бестолковой работ и выполнение её бесплатно, типа субботников"
    },
    "title": {
      "languageTag": "ru-RU",
      "text": "Типичный день на работе"
    },
    "tweetAutoFillText": "ОАО \"РЖД\" review on #indeedjobs: \"Типичный день на работе\"",
    "type": "LIST",
    "unhelpful": 0,
    "workAndLifeBalanceRating": {
      "rating": 2,
      "type": "Job Work/Life Balance"
    }
  },
  {
    "comments": [],
    "compensationAndBenefitsRating": {
      "rating": 4,
      "type": "Compensation/Benefits"
    },
    "cons": {
      "languageTag": "ru-RU",
      "text": "Нет"
    },
    "country": "RU",
    "cultureAndValuesRating": {
      "rating": 3,
      "type": "Job Culture"
    },
    "currentEmployee": true,
    "encryptedReviewId": "b19f04db7ffe8513",
    "headerTitle": "ОАО \"РЖД\" Оператор по обслуживанию и ремонту вагонов и контейнеров Review - Регулярная зарплата",
    "helpful": 0,
    "indexable": false,
    "isDeletable": false,
    "jobSecurityAndAdvancementRating": {
      "rating": 3,
      "type": "Job Security/Advancement"
    },
    "jobTitle": "Оператор по обслуживанию и ремонту вагонов и контейнеров",
    "jobTitleFilterLink": "/cmp/%D0%9E%D0%B0%D0%BE-%22%D1%80%D0%B6%D0%B4%22/reviews?fjobtitle=%D0%9C%D0%B0%D1%81%D1%82%D0%B5%D1%80+%D0%BF%D0%BE+%D1%80%D0%B5%D0%BC%D0%BE%D0%BD%D1%82%D1%83",
    "location": "Малошуйка",
    "locationFilterLink": "/cmp/%D0%9E%D0%B0%D0%BE-%22%D1%80%D0%B6%D0%B4%22/reviews?fcountry=RU&floc=%D0%9C%D0%B0%D0%BB%D0%BE%D1%88%D1%83%D0%B9%D0%BA%D0%B0",
    "managementRating": {
      "rating": 3,
      "type": "Management"
    },
    "normJobTitle": "Мастер по ремонту",
    "overallRating": 4,
    "pros": {
      "languageTag": "ru-RU",
      "text": "Зарплата"
    },
    "redacted": false,
    "reviewUid": "1edmsft1u38n4000",
    "reviewUrl": "/cmp/%D0%9E%D0%B0%D0%BE-%22%D1%80%D0%B6%D0%B4%22/reviews/%D1%80%D0%B5%D0%B3%D1%83%D0%BB%D1%8F%D1%80%D0%BD%D0%B0%D1%8F-%D0%B7%D0%B0%D1%80%D0%BF%D0%BB%D0%B0%D1%82%D0%B0?id=b19f04db7ffe8513",
    "sharingLink": "https://www.indeed.com/cmp/%D0%9E%D0%B0%D0%BE-%22%D1%80%D0%B6%D0%B4%22/reviews/%D1%80%D0%B5%D0%B3%D1%83%D0%BB%D1%8F%D1%80%D0%BD%D0%B0%D1%8F-%D0%B7%D0%B0%D1%80%D0%BF%D0%BB%D0%B0%D1%82%D0%B0?id=b19f04db7ffe8513",
    "submissionDate": "July 20, 2020",
    "text": {
      "languageTag": "ru-RU",
      "text": "Регулярная зарплата, соблюдение корпоративной этики"
    },
    "title": {
      "languageTag": "ru-RU",
      "text": "Регулярная зарплата"
    },
    "tweetAutoFillText": "ОАО \"РЖД\" review on #indeedjobs: \"Регулярная зарплата\"",
    "type": "LIST",
    "unhelpful": 0,
    "workAndLifeBalanceRating": {
      "rating": 4,
      "type": "Job Work/Life Balance"
    }
  },
  {
    "comments": [],
    "compensationAndBenefitsRating": {
      "rating": 1,
      "type": "Compensation/Benefits"
    },
    "cons": {
      "languageTag": "ru-RU",
      "text": "Очень много"
    },
    "country": "RU",
    "cultureAndValuesRating": {
      "rating": 1,
      "type": "Job Culture"
    },
    "currentEmployee": false,
    "encryptedReviewId": "d1da9074b2c60436",
    "headerTitle": "ОАО \"РЖД\" Техник Review - Работа в ржд",
    "helpful": 0,
    "indexable": true,
    "isDeletable": false,
    "jobSecurityAndAdvancementRating": {
      "rating": 1,
      "type": "Job Security/Advancement"
    },
    "jobTitle": "Техник",
    "jobTitleFilterLink": "/cmp/%D0%9E%D0%B0%D0%BE-%22%D1%80%D0%B6%D0%B4%22/reviews?fjobtitle=%D0%A2%D0%B5%D1%85%D0%BD%D0%B8%D0%BA",
    "location": "Иваново",
    "locationFilterLink": "/cmp/%D0%9E%D0%B0%D0%BE-%22%D1%80%D0%B6%D0%B4%22/reviews?fcountry=RU&floc=%D0%98%D0%B2%D0%B0%D0%BD%D0%BE%D0%B2%D0%BE",
    "managementRating": {
      "rating": 1,
      "type": "Management"
    },
    "normJobTitle": "Техник",
    "overallRating": 1,
    "pros": {
      "languageTag": "ru-RU",
      "text": "Нет"
    },
    "redacted": false,
    "reviewUid": "1ecpgiblv399j000",
    "reviewUrl": "/cmp/%D0%9E%D0%B0%D0%BE-%22%D1%80%D0%B6%D0%B4%22/reviews/%D1%80%D0%B0%D0%B1%D0%BE%D1%82%D0%B0-%D0%B2-%D1%80%D0%B6%D0%B4?id=d1da9074b2c60436",
    "sharingLink": "https://www.indeed.com/cmp/%D0%9E%D0%B0%D0%BE-%22%D1%80%D0%B6%D0%B4%22/reviews/%D1%80%D0%B0%D0%B1%D0%BE%D1%82%D0%B0-%D0%B2-%D1%80%D0%B6%D0%B4?id=d1da9074b2c60436",
    "submissionDate": "July 9, 2020",
    "text": {
      "languageTag": "ru-RU",
      "text": "Хотите быть никем и чтобы звали вас никак? Тогда приходите работать в РЖД! Здесь вам гарантированы постоянные нагоняи от начальства любого ранга; обед в кустах урывками; ежемесячные лишения премии;  стрессы, ночные кошмары. А самое главное - вас в любой момент могут выкинуть на улицу, несмотря на стаж работы, возраст, семейное положение и наличие несовершеннолетних детей. Да здравствует РЖД!"
    },
    "title": {
      "languageTag": "ru-RU",
      "text": "Работа в ржд"
    },
    "tweetAutoFillText": "ОАО \"РЖД\" review on #indeedjobs: \"Работа в ржд\"",
    "type": "LIST",
    "unhelpful": 0,
    "workAndLifeBalanceRating": {
      "rating": 1,
      "type": "Job Work/Life Balance"
    }
  },
  {
    "comments": [],
    "compensationAndBenefitsRating": {
      "rating": 4,
      "type": "Compensation/Benefits"
    },
    "cons": {
      "languageTag": "ru-RU",
      "text": "Нарушение трудового законодательства как работниками, так и руководством."
    },
    "country": "RU",
    "cultureAndValuesRating": {
      "rating": 2,
      "type": "Job Culture"
    },
    "currentEmployee": false,
    "encryptedReviewId": "e8c8d70b96beebcf",
    "headerTitle": "ОАО \"РЖД\" электромеханик СЦБ Review - Большое количество стрессовых ситуаций",
    "helpful": 0,
    "indexable": false,
    "isDeletable": false,
    "jobSecurityAndAdvancementRating": {
      "rating": 3,
      "type": "Job Security/Advancement"
    },
    "jobTitle": "электромеханик СЦБ",
    "jobTitleFilterLink": "/cmp/%D0%9E%D0%B0%D0%BE-%22%D1%80%D0%B6%D0%B4%22/reviews?fjobtitle=%D0%AD%D0%BB%D0%B5%D0%BA%D1%82%D1%80%D0%BE%D0%BC%D0%B5%D1%85%D0%B0%D0%BD%D0%B8%D0%BA",
    "location": "Астрахань",
    "locationFilterLink": "/cmp/%D0%9E%D0%B0%D0%BE-%22%D1%80%D0%B6%D0%B4%22/reviews?fcountry=RU&floc=%D0%90%D1%81%D1%82%D1%80%D0%B0%D1%85%D0%B0%D0%BD%D1%8C",
    "managementRating": {
      "rating": 3,
      "type": "Management"
    },
    "normJobTitle": "Электромеханик",
    "overallRating": 3,
    "pros": {
      "languageTag": "ru-RU",
      "text": "Бесплатный билет для проезда в отпуск"
    },
    "redacted": false,
    "reviewUid": "1ecn41njnp9m0800",
    "reviewUrl": "/cmp/%D0%9E%D0%B0%D0%BE-%22%D1%80%D0%B6%D0%B4%22/reviews/%D0%B1%D0%BE%D0%BB%D1%8C%D1%88%D0%BE%D0%B5-%D0%BA%D0%BE%D0%BB%D0%B8%D1%87%D0%B5%D1%81%D1%82%D0%B2%D0%BE-%D1%81%D1%82%D1%80%D0%B5%D1%81%D1%81%D0%BE%D0%B2%D1%8B%D1%85-%D1%81%D0%B8%D1%82%D1%83%D0%B0%D1%86%D0%B8%D0%B9?id=e8c8d70b96beebcf",
    "sharingLink": "https://www.indeed.com/cmp/%D0%9E%D0%B0%D0%BE-%22%D1%80%D0%B6%D0%B4%22/reviews/%D0%B1%D0%BE%D0%BB%D1%8C%D1%88%D0%BE%D0%B5-%D0%BA%D0%BE%D0%BB%D0%B8%D1%87%D0%B5%D1%81%D1%82%D0%B2%D0%BE-%D1%81%D1%82%D1%80%D0%B5%D1%81%D1%81%D0%BE%D0%B2%D1%8B%D1%85-%D1%81%D0%B8%D1%82%D1%83%D0%B0%D1%86%D0%B8%D0%B9?id=e8c8d70b96beebcf",
    "submissionDate": "July 8, 2020",
    "text": {
      "languageTag": "ru-RU",
      "text": "Постоянное нахождение на связи с диспетчерским аппаратом и руководством, при большом стаже работы, убивает нервную систему"
    },
    "title": {
      "languageTag": "ru-RU",
      "text": "Большое количество стрессовых ситуаций"
    },
    "tweetAutoFillText": "ОАО \"РЖД\" review on #indeedjobs: \"Большое количество стрессовых ситуаций\"",
    "type": "LIST",
    "unhelpful": 0,
    "workAndLifeBalanceRating": {
      "rating": 4,
      "type": "Job Work/Life Balance"
    }
  },
  {
    "comments": [],
    "compensationAndBenefitsRating": {
      "rating": 1,
      "type": "Compensation/Benefits"
    },
    "country": "RU",
    "cultureAndValuesRating": {
      "rating": 1,
      "type": "Job Culture"
    },
    "currentEmployee": false,
    "encryptedReviewId": "5e4aa28038567f0e",
    "headerTitle": "ОАО \"РЖД\" Фельдшер ПРМО Review - До 2018 года можно было работать в больнице ОАО РЖ, далее не возможно, очень трудно не понимание в коллективе другдруга.",
    "helpful": 0,
    "indexable": false,
    "isDeletable": false,
    "jobSecurityAndAdvancementRating": {
      "rating": 1,
      "type": "Job Security/Advancement"
    },
    "jobTitle": "Фельдшер ПРМО",
    "jobTitleFilterLink": "/cmp/%D0%9E%D0%B0%D0%BE-%22%D1%80%D0%B6%D0%B4%22/reviews?fjobtitle=%D0%A4%D0%B5%D0%BB%D1%8C%D0%B4%D1%88%D0%B5%D1%80",
    "location": "Комсомольск-на-Амуре",
    "locationFilterLink": "/cmp/%D0%9E%D0%B0%D0%BE-%22%D1%80%D0%B6%D0%B4%22/reviews?fcountry=RU&floc=%D0%9A%D0%BE%D0%BC%D1%81%D0%BE%D0%BC%D0%BE%D0%BB%D1%8C%D1%81%D0%BA-%D0%BD%D0%B0-%D0%90%D0%BC%D1%83%D1%80%D0%B5",
    "managementRating": {
      "rating": 1,
      "type": "Management"
    },
    "normJobTitle": "Фельдшер",
    "overallRating": 4,
    "redacted": false,
    "reviewUid": "1e9febqg63d32000",
    "reviewUrl": "/cmp/%D0%9E%D0%B0%D0%BE-%22%D1%80%D0%B6%D0%B4%22/reviews/%D0%B4%D0%BE-2018-%D0%B3%D0%BE%D0%B4%D0%B0-%D0%BC%D0%BE%D0%B6%D0%BD%D0%BE-%D0%B1%D1%8B%D0%BB%D0%BE-%D1%80%D0%B0%D0%B1%D0%BE%D1%82%D0%B0%D1%82%D1%8C-%D0%B2-%D0%B1%D0%BE%D0%BB%D1%8C%D0%BD%D0%B8%D1%86%D0%B5-%D0%BE%D0%B0%D0%BE-%D1%80%D0%B6-%D0%B4%D0%B0%D0%BB%D0%B5%D0%B5-%D0%BD%D0%B5-%D0%B2%D0%BE%D0%B7%D0%BC%D0%BE%D0%B6%D0%BD%D0%BE-%D0%BE%D1%87%D0%B5%D0%BD%D1%8C-%D1%82%D1%80%D1%83%D0%B4%D0%BD%D0%BE-%D0%BD%D0%B5-%D0%BF%D0%BE%D0%BD%D0%B8%D0%BC%D0%B0%D0%BD%D0%B8%D0%B5-%D0%B2-%D0%BA%D0%BE%D0%BB%D0%BB%D0%B5%D0%BA%D1%82%D0%B8%D0%B2%D0%B5-%D0%B4%D1%80%D1%83%D0%B3%D0%B4%D1%80%D1%83%D0%B3%D0%B0?id=5e4aa28038567f0e",
    "sharingLink": "https://www.indeed.com/cmp/%D0%9E%D0%B0%D0%BE-%22%D1%80%D0%B6%D0%B4%22/reviews/%D0%B4%D0%BE-2018-%D0%B3%D0%BE%D0%B4%D0%B0-%D0%BC%D0%BE%D0%B6%D0%BD%D0%BE-%D0%B1%D1%8B%D0%BB%D0%BE-%D1%80%D0%B0%D0%B1%D0%BE%D1%82%D0%B0%D1%82%D1%8C-%D0%B2-%D0%B1%D0%BE%D0%BB%D1%8C%D0%BD%D0%B8%D1%86%D0%B5-%D0%BE%D0%B0%D0%BE-%D1%80%D0%B6-%D0%B4%D0%B0%D0%BB%D0%B5%D0%B5-%D0%BD%D0%B5-%D0%B2%D0%BE%D0%B7%D0%BC%D0%BE%D0%B6%D0%BD%D0%BE-%D0%BE%D1%87%D0%B5%D0%BD%D1%8C-%D1%82%D1%80%D1%83%D0%B4%D0%BD%D0%BE-%D0%BD%D0%B5-%D0%BF%D0%BE%D0%BD%D0%B8%D0%BC%D0%B0%D0%BD%D0%B8%D0%B5-%D0%B2-%D0%BA%D0%BE%D0%BB%D0%BB%D0%B5%D0%BA%D1%82%D0%B8%D0%B2%D0%B5-%D0%B4%D1%80%D1%83%D0%B3%D0%B4%D1%80%D1%83%D0%B3%D0%B0?id=5e4aa28038567f0e",
    "submissionDate": "May 29, 2020",
    "text": {
      "languageTag": "ru-RU",
      "text": "Ни чего хорошего и плохого тоже. Но я там больше работать не хочу, того коллектива который был уже нет."
    },
    "title": {
      "languageTag": "ru-RU",
      "text": "До 2018 года можно было работать в больнице ОАО РЖ, далее не возможно, очень трудно не понимание в коллективе другдруга."
    },
    "tweetAutoFillText": "ОАО \"РЖД\" review on #indeedjobs: \"До 2018 года можно было работать в больнице ОАО РЖ, далее не возможно, очень…\"",
    "type": "LIST",
    "unhelpful": 0,
    "workAndLifeBalanceRating": {
      "rating": 2,
      "type": "Job Work/Life Balance"
    }
  },
  {
    "comments": [],
    "compensationAndBenefitsRating": {
      "rating": 1,
      "type": "Compensation/Benefits"
    },
    "country": "RU",
    "cultureAndValuesRating": {
      "rating": 1,
      "type": "Job Culture"
    },
    "currentEmployee": false,
    "encryptedReviewId": "6d1b1089be6da4b5",
    "headerTitle": "ОАО \"РЖД\" Оператор при дсп Review - Врагу не пожелаешь",
    "helpful": 0,
    "indexable": false,
    "isDeletable": false,
    "jobSecurityAndAdvancementRating": {
      "rating": 1,
      "type": "Job Security/Advancement"
    },
    "jobTitle": "Оператор при дсп",
    "jobTitleFilterLink": "/cmp/%D0%9E%D0%B0%D0%BE-%22%D1%80%D0%B6%D0%B4%22/reviews?fjobtitle=%D0%9E%D0%BF%D0%B5%D1%80%D0%B0%D1%82%D0%BE%D1%80",
    "location": "Кутум",
    "managementRating": {
      "rating": 1,
      "type": "Management"
    },
    "normJobTitle": "Оператор",
    "overallRating": 1,
    "redacted": false,
    "reviewUid": "1e98uprppr93c800",
    "reviewUrl": "/cmp/%D0%9E%D0%B0%D0%BE-%22%D1%80%D0%B6%D0%B4%22/reviews/%D0%B2%D1%80%D0%B0%D0%B3%D1%83-%D0%BD%D0%B5-%D0%BF%D0%BE%D0%B6%D0%B5%D0%BB%D0%B0%D0%B5%D1%88%D1%8C?id=6d1b1089be6da4b5",
    "sharingLink": "https://www.indeed.com/cmp/%D0%9E%D0%B0%D0%BE-%22%D1%80%D0%B6%D0%B4%22/reviews/%D0%B2%D1%80%D0%B0%D0%B3%D1%83-%D0%BD%D0%B5-%D0%BF%D0%BE%D0%B6%D0%B5%D0%BB%D0%B0%D0%B5%D1%88%D1%8C?id=6d1b1089be6da4b5",
    "submissionDate": "May 26, 2020",
    "text": {
      "languageTag": "ru-RU",
      "text": "Никаких условий,только постоянно всем должен,зарплата маленькая,а обязанностей куча,карьерного роста нет,если нет связей"
    },
    "title": {
      "languageTag": "ru-RU",
      "text": "Врагу не пожелаешь"
    },
    "tweetAutoFillText": "ОАО \"РЖД\" review on #indeedjobs: \"Врагу не пожелаешь\"",
    "type": "LIST",
    "unhelpful": 0,
    "workAndLifeBalanceRating": {
      "rating": 1,
      "type": "Job Work/Life Balance"
    }
  },
  {
    "comments": [],
    "compensationAndBenefitsRating": {
      "rating": 3,
      "type": "Compensation/Benefits"
    },
    "country": "RU",
    "cultureAndValuesRating": {
      "rating": 3,
      "type": "Job Culture"
    },
    "currentEmployee": false,
    "encryptedReviewId": "7e49e829e4b809b2",
    "headerTitle": "ОАО \"РЖД\" Электромонтер Review - Продуктивная, опасная, неблагоприятная",
    "helpful": 1,
    "indexable": false,
    "isDeletable": false,
    "jobSecurityAndAdvancementRating": {
      "rating": 3,
      "type": "Job Security/Advancement"
    },
    "jobTitle": "Электромонтер",
    "jobTitleFilterLink": "/cmp/%D0%9E%D0%B0%D0%BE-%22%D1%80%D0%B6%D0%B4%22/reviews?fjobtitle=%D0%AD%D0%BB%D0%B5%D0%BA%D1%82%D1%80%D0%BE%D0%BC%D0%BE%D0%BD%D1%82%D0%B5%D1%80",
    "location": "СЦБ",
    "managementRating": {
      "rating": 1,
      "type": "Management"
    },
    "normJobTitle": "Электромонтер",
    "overallRating": 2,
    "redacted": false,
    "reviewUid": "1e6l3rdpjnm6v800",
    "reviewUrl": "/cmp/%D0%9E%D0%B0%D0%BE-%22%D1%80%D0%B6%D0%B4%22/reviews/%D0%BF%D1%80%D0%BE%D0%B4%D1%83%D0%BA%D1%82%D0%B8%D0%B2%D0%BD%D0%B0%D1%8F-%D0%BE%D0%BF%D0%B0%D1%81%D0%BD%D0%B0%D1%8F-%D0%BD%D0%B5%D0%B1%D0%BB%D0%B0%D0%B3%D0%BE%D0%BF%D1%80%D0%B8%D1%8F%D1%82%D0%BD%D0%B0%D1%8F?id=7e49e829e4b809b2",
    "sharingLink": "https://www.indeed.com/cmp/%D0%9E%D0%B0%D0%BE-%22%D1%80%D0%B6%D0%B4%22/reviews/%D0%BF%D1%80%D0%BE%D0%B4%D1%83%D0%BA%D1%82%D0%B8%D0%B2%D0%BD%D0%B0%D1%8F-%D0%BE%D0%BF%D0%B0%D1%81%D0%BD%D0%B0%D1%8F-%D0%BD%D0%B5%D0%B1%D0%BB%D0%B0%D0%B3%D0%BE%D0%BF%D1%80%D0%B8%D1%8F%D1%82%D0%BD%D0%B0%D1%8F?id=7e49e829e4b809b2",
    "submissionDate": "April 23, 2020",
    "text": {
      "languageTag": "ru-RU",
      "text": "Не нормированные рабочее время в не зависимости от должности, переработки не оплачиваются, руководство закрывает глаза на нарушение техники безопасности, мотивируя ситуацию тем, что задание должно быть выполнено, нет чоткого распределения обязанностей, один работник может исполнять обязанности на уровень в два раза выше, хотя зарплата будет фиксированной, когда как если последствия выполнения обязанностей выше влекут за собой некие нарушения, отвечать будет по всем правилам и пунктам, готовьтесь раскошелиться на инструмент для выполнения своих обязанностей. Не соблюдают действия трудового договора. Могут легко подставить."
    },
    "title": {
      "languageTag": "ru-RU",
      "text": "Продуктивная, опасная, неблагоприятная"
    },
    "tweetAutoFillText": "ОАО \"РЖД\" review on #indeedjobs: \"Продуктивная, опасная, неблагоприятная\"",
    "type": "LIST",
    "unhelpful": 0,
    "workAndLifeBalanceRating": {
      "rating": 1,
      "type": "Job Work/Life Balance"
    }
  },
  {
    "comments": [],
    "compensationAndBenefitsRating": {
      "rating": 2,
      "type": "Compensation/Benefits"
    },
    "country": "RU",
    "cultureAndValuesRating": {
      "rating": 1,
      "type": "Job Culture"
    },
    "currentEmployee": false,
    "encryptedReviewId": "b58f8428302179f8",
    "headerTitle": "ОАО \"РЖД\" Машинист ДЭС передвижной Review - Не советую",
    "helpful": 0,
    "indexable": false,
    "isDeletable": false,
    "jobSecurityAndAdvancementRating": {
      "rating": 2,
      "type": "Job Security/Advancement"
    },
    "jobTitle": "Машинист ДЭС передвижной",
    "jobTitleFilterLink": "/cmp/%D0%9E%D0%B0%D0%BE-%22%D1%80%D0%B6%D0%B4%22/reviews?fjobtitle=%D0%9C%D0%B0%D1%88%D0%B8%D0%BD%D0%B8%D1%81%D1%82+%D0%94%D0%AD%D0%A1+%D0%BF%D0%B5%D1%80%D0%B5%D0%B4%D0%B2%D0%B8%D0%B6%D0%BD%D0%BE%D0%B9",
    "location": "Сургут",
    "locationFilterLink": "/cmp/%D0%9E%D0%B0%D0%BE-%22%D1%80%D0%B6%D0%B4%22/reviews?fcountry=RU&floc=%D0%A1%D1%83%D1%80%D0%B3%D1%83%D1%82",
    "managementRating": {
      "rating": 1,
      "type": "Management"
    },
    "normJobTitle": "Машинист ДЭС передвижной",
    "overallRating": 3,
    "redacted": false,
    "reviewUid": "1e34qjjekostc803",
    "reviewUrl": "/cmp/%D0%9E%D0%B0%D0%BE-%22%D1%80%D0%B6%D0%B4%22/reviews/%D0%BD%D0%B5-%D1%81%D0%BE%D0%B2%D0%B5%D1%82%D1%83%D1%8E?id=b58f8428302179f8",
    "sharingLink": "https://www.indeed.com/cmp/%D0%9E%D0%B0%D0%BE-%22%D1%80%D0%B6%D0%B4%22/reviews/%D0%BD%D0%B5-%D1%81%D0%BE%D0%B2%D0%B5%D1%82%D1%83%D1%8E?id=b58f8428302179f8",
    "submissionDate": "March 11, 2020",
    "text": {
      "languageTag": "ru-RU",
      "text": "Работа не соответсвует оплате труда, за совмещение не платят, и не указывают в трудовой книжке."
    },
    "title": {
      "languageTag": "ru-RU",
      "text": "Не советую"
    },
    "tweetAutoFillText": "ОАО \"РЖД\" review on #indeedjobs: \"Не советую\"",
    "type": "LIST",
    "unhelpful": 0,
    "workAndLifeBalanceRating": {
      "rating": 3,
      "type": "Job Work/Life Balance"
    }
  }
]